odoo10_addon_attachment_attach_non_editable-10.0.1.0.0.99.dev3-py2.7-nspkg.pth
odoo/addons/attachment_attach_non_editable/README.rst
odoo/addons/attachment_attach_non_editable/__init__.py
odoo/addons/attachment_attach_non_editable/__manifest__.py
odoo/addons/attachment_attach_non_editable/i18n/attachment_attach_non_editable.pot
odoo/addons/attachment_attach_non_editable/static/description/icon.png
odoo/addons/attachment_attach_non_editable/static/src/js/sidebar.js
odoo/addons/attachment_attach_non_editable/static/src/xml/sidebar.xml
odoo/addons/attachment_attach_non_editable/templates/web.xml
odoo10_addon_attachment_attach_non_editable-10.0.1.0.0.99.dev3.dist-info/METADATA
odoo10_addon_attachment_attach_non_editable-10.0.1.0.0.99.dev3.dist-info/RECORD
odoo10_addon_attachment_attach_non_editable-10.0.1.0.0.99.dev3.dist-info/WHEEL
odoo10_addon_attachment_attach_non_editable-10.0.1.0.0.99.dev3.dist-info/namespace_packages.txt
odoo10_addon_attachment_attach_non_editable-10.0.1.0.0.99.dev3.dist-info/top_level.txt
